[
    {
     "id":1,
      "title":"Paris Hotel-907 BeckFord Dr",
      "location":"8856 Pecan St.",
      "image":"./images/paris1.jpg",
      "room" : "9 Room",
      "for":"ForRent",
      "bed" : "20 Bed",
      "bath":" 2 Bath",
       "area": "798 sqft"
       },
    {
        "id":2,
        "title":"QH Hotel-907 paris Dr",
        "location":"8855 Pecas St.",
         "image":"./images/paris1.jpg",
         "room" : "2 Room",
      "for":"ForRent",
        "bed" : "3 Bed",
        "bath":" 1 Bath",
         "area": "724 sqft"
    },
    {
        "id":3,
        "title":"RM Quarter B-907 BeckFord DL",
        "image":"./images/paris2.jpg",
        "for":"ForRent",
        "location":"8856 Necang St.",
        "room" : "3 Room",
        "bed" : "4 Bed",
        "bath":" 1 Bath",
         "area": "723 sqft"
    },
    {
        "id":4,
        "title":"PR Hilton-905 BeckFord LD",
      "image":"./images/pexels-paul-basel-1816823.jpg",
      "location":"9856 Secan St.",
        "room" : "4 Room",
      "for":"ForRent",
      "bed" : "6 Bed",
        "bath":" 3 Bath",
         "area": "723 sqft"
    },
    {
        "id":5,
        "title":"Hotel Queen H-506 BeckFord Dr",
        "location":"8856 Pecan St.",
        "room" : "6 Room",
      "image":"./images/pexels-lukas-kloeppel-466685.jpg",
      "for":"ForRent",
      "bed" : "9 Bed",
        "bath":" 3 Bath",
         "area": "850 sqft"
    },
    {
        "id":6,
        "title":"Band Deen-908 BeckFord Dr",
        "location":"8858 Decan St.",
        "room" : "5 Room",
      "image":"./images/paris3.jpg",
      "for":"ForRent",
      "bed" : "8 Bed",
      "bath":" 1 Bath",
      "area": "725 sqft"
    },
    {
        "id":7,
        "title":"NewYolo H-907 BeckFord Dr",
        "location":"8859 Stand St.",
      "image":"./images/maxbender.jpg",
      "for":"ForRent",
      "room" : "8 Room",
        "bed" : "10Bed",
        "bath":" 5 Bath",
         "area": "655 sft"
    },
    {
        "id":8,
        "title":"RCE Theater-907 BeckFord Dr",
        "location":"8856 Pecan St.",
        "room" : "1 Room",
        "bed" : "2 Bed",
      "for":"ForRent",
      "image":"./images/pexels-paul-basel-1816823.jpg",
      "bath":" 1 Bath",
         "area": "728 sft"
    },
    {
     "id":9,
     "title":"RCE Theater-907 BeckFord Dr",
     "location":"8856 Pecan St.",
      "image":"./images/pexels-soly-moses-14825208.jpg",
      "room" : "3 Room",
      "for":"ForRent",

        "bed" : "4 Bed",
        "bath":" 1 Bath",
         "area": "723 sft"
    }
]